[{"lastname":"Casey","firstname":"Ellis","id":8766110},{"lastname":"Cabrera","firstname":"Shyann","id":2776306},{"lastname":"Clayton","firstname":"Shelby","id":2740156},{"lastname":"Carney","firstname":"Quinton","id":1818833},{"lastname":"Cooper","firstname":"Cason","id":6999721},{"lastname":"Case","firstname":"Brayden","id":4771616},{"lastname":"Christensen","firstname":"Jean","id":9554246},{"lastname":"Cole","firstname":"Margaret","id":7943669},{"lastname":"Charles","firstname":"Amiyah","id":1196279},{"lastname":"Chavez","firstname":"Derrick","id":3360398},{"lastname":"Conrad","firstname":"Sean","id":1047574},{"lastname":"Church","firstname":"Axel","id":2217189},{"lastname":"Cervantes","firstname":"Piper","id":2666942},{"lastname":"Cooley","firstname":"Micaela","id":2970603},{"lastname":"Cox","firstname":"Siena","id":7439788},{"lastname":"Camacho","firstname":"Trevor","id":8750821},{"lastname":"Collier","firstname":"Chana","id":2950848},{"lastname":"Callahan","firstname":"Lexie","id":3050108},{"lastname":"Caldwell","firstname":"Atticus","id":4193659},{"lastname":"Conley","firstname":"Amina","id":7090399},{"lastname":"Carroll","firstname":"Jaelynn","id":3854779},{"lastname":"Cardenas","firstname":"Paulina","id":2522354},{"lastname":"Chaney","firstname":"Yusuf","id":9461902},{"lastname":"Contreras","firstname":"Nicole","id":7638326},{"lastname":"Castro","firstname":"Roy","id":9221189},{"lastname":"Cuevas","firstname":"Braiden","id":4483042},{"lastname":"Carr","firstname":"Sheldon","id":8761899},{"lastname":"Colon","firstname":"River","id":5665123},{"lastname":"Cameron","firstname":"Kathleen","id":7435629},{"lastname":"Craig","firstname":"Deegan","id":2456439},{"lastname":"Carpenter","firstname":"Levi","id":1782819},{"lastname":"Christian","firstname":"Clinton","id":1240194},{"lastname":"Cobb","firstname":"Camila","id":7487526},{"lastname":"Chung","firstname":"Noelle","id":5474168},{"lastname":"Clay","firstname":"Cole","id":2350346},{"lastname":"Chase","firstname":"Paula","id":6719295},{"lastname":"Campos","firstname":"Zion","id":9424280},{"lastname":"Chandler","firstname":"Ally","id":4903517},{"lastname":"Curry","firstname":"Jaylen","id":6838496},{"lastname":"Cross","firstname":"Lilian","id":8388226},{"lastname":"Carlson","firstname":"Jordyn","id":1620938},{"lastname":"Compton","firstname":"Brynlee","id":5191578},{"lastname":"Carson","firstname":"Raul","id":9206925},{"lastname":"Cummings","firstname":"Nathen","id":2292333},{"lastname":"Cantu","firstname":"Marshall","id":1922233},{"lastname":"Carey","firstname":"Ace","id":3668980},{"lastname":"Coffey","firstname":"Lucas","id":1140193},{"lastname":"Cohen","firstname":"Dwayne","id":6825667},{"lastname":"Collins","firstname":"Trey","id":2745288},{"lastname":"Clark","firstname":"Rishi","id":2432011},{"lastname":"Cooke","firstname":"Keyla","id":6741562},{"lastname":"Cherry","firstname":"Ahmed","id":1328782},{"lastname":"Cruz","firstname":"Thalia","id":2450191},{"lastname":"Chen","firstname":"Celia","id":4385715},{"lastname":"Cline","firstname":"Summer","id":6162886},{"lastname":"Choi","firstname":"Cesar","id":9998306},{"lastname":"Carter","firstname":"Mira","id":7877242},{"lastname":"Cortez","firstname":"Jacey","id":5541822},{"lastname":"Costa","firstname":"Cody","id":5572564},{"lastname":"Cook","firstname":"Leo","id":9418513},{"lastname":"Calhoun","firstname":"Colby","id":3844505},{"lastname":"Coleman","firstname":"Konnor","id":8188199},{"lastname":"Cannon","firstname":"Larry","id":8491022},{"lastname":"Conway","firstname":"Riley","id":3136370},{"lastname":"Cunningham","firstname":"Raquel","id":4632587},{"lastname":"Cisneros","firstname":"Giovani","id":1585822},{"lastname":"Chang","firstname":"Cortez","id":3852220},{"lastname":"Chapman","firstname":"Ishaan","id":8953830},{"lastname":"Cowan","firstname":"Dominique","id":4289849},{"lastname":"Crawford","firstname":"Lorelei","id":5316271},{"lastname":"Chan","firstname":"Karsyn","id":3440687},{"lastname":"Calderon","firstname":"Priscilla","id":5081990},{"lastname":"Curtis","firstname":"Brayden","id":4301251},{"lastname":"Copeland","firstname":"Gavyn","id":9654925},{"lastname":"Chambers","firstname":"Rebecca","id":2204029},{"lastname":"Crosby","firstname":"Aliza","id":6100066},{"lastname":"Cain","firstname":"Alicia","id":5522084},{"lastname":"Cantrell","firstname":"Mariyah","id":2153355},{"lastname":"Campbell","firstname":"Emmett","id":4825328},{"lastname":"Combs","firstname":"Adonis","id":3664979},{"lastname":"Castaneda","firstname":"Fernando","id":3989399},{"lastname":"Clements","firstname":"Gabriela","id":7152579},{"lastname":"Cordova","firstname":"Hailey","id":5042892},{"lastname":"Crane","firstname":"Weston","id":1678554},{"lastname":"Clarke","firstname":"Ellen","id":7157910},{"lastname":"Cochran","firstname":"Leonel","id":4864764},{"lastname":"Castillo","firstname":"Eileen","id":9798361},{"lastname":"Carrillo","firstname":"Dereon","id":6276568},{"lastname":"Conner","firstname":"Aydin","id":1697951},{"lastname":"Crane","firstname":"Nikolai","id":5815657},{"lastname":"Calhoun","firstname":"Jose","id":5539920},{"lastname":"Chang","firstname":"Aspen","id":2275441},{"lastname":"Cherry","firstname":"Mariyah","id":3045538},{"lastname":"Clay","firstname":"Maddox","id":9265950},{"lastname":"Cannon","firstname":"Ernesto","id":1015877},{"lastname":"Craig","firstname":"Kameron","id":8412232},{"lastname":"Conway","firstname":"Britney","id":5352923},{"lastname":"Cline","firstname":"Jordon","id":1622792},{"lastname":"Cain","firstname":"Frankie","id":2256808},{"lastname":"Carter","firstname":"Sarahi","id":8214778},{"lastname":"Callahan","firstname":"Randall","id":7182353},{"lastname":"Carr","firstname":"Elsa","id":7063898},{"lastname":"Cordova","firstname":"Marshall","id":1571653},{"lastname":"Coleman","firstname":"Jacey","id":5657164},{"lastname":"Cummings","firstname":"Raul","id":2747228},{"lastname":"Castro","firstname":"Mariana","id":3286770},{"lastname":"Carson","firstname":"Gordon","id":3573966},{"lastname":"Coffey","firstname":"Micaela","id":6485197},{"lastname":"Castillo","firstname":"Phoebe","id":1146550},{"lastname":"Clements","firstname":"Levi","id":1663781},{"lastname":"Clayton","firstname":"Leo","id":7134245},{"lastname":"Curry","firstname":"Keyla","id":9887092},{"lastname":"Curtis","firstname":"Henry","id":8969883},{"lastname":"Charles","firstname":"Cedric","id":8308399},{"lastname":"Compton","firstname":"Jordin","id":6262890},{"lastname":"Castaneda","firstname":"Gwendolyn","id":2329304},{"lastname":"Cohen","firstname":"Miranda","id":2538727},{"lastname":"Cuevas","firstname":"Elaina","id":1303556},{"lastname":"Carlson","firstname":"Skyla","id":3124124},{"lastname":"Camacho","firstname":"Rocco","id":3651379},{"lastname":"Cook","firstname":"Madalyn","id":1313293},{"lastname":"Choi","firstname":"Lea","id":9436567},{"lastname":"Christensen","firstname":"Mariam","id":8033845},{"lastname":"Carney","firstname":"Emery","id":9952090},{"lastname":"Cortez","firstname":"Cason","id":2077755},{"lastname":"Campos","firstname":"Brittany","id":2782855},{"lastname":"Chavez","firstname":"Marquise","id":9145103},{"lastname":"Cross","firstname":"Jaylen","id":4323002},{"lastname":"Cole","firstname":"Ernest","id":6157546},{"lastname":"Costa","firstname":"Reese","id":9387030},{"lastname":"Crawford","firstname":"Gilbert","id":8782892},{"lastname":"Carey","firstname":"Journey","id":3233078},{"lastname":"Campbell","firstname":"Miracle","id":5257799},{"lastname":"Conner","firstname":"Jakob","id":6263407},{"lastname":"Cardenas","firstname":"Levi","id":6565554},{"lastname":"Copeland","firstname":"Aspen","id":3439911},{"lastname":"Conrad","firstname":"Bailey","id":9246376},{"lastname":"Combs","firstname":"Jairo","id":6056567},{"lastname":"Contreras","firstname":"Tristen","id":7558284},{"lastname":"Calderon","firstname":"Miracle","id":8939018},{"lastname":"Cooke","firstname":"Hassan","id":9221624},{"lastname":"Chung","firstname":"Cassandra","id":8509207},{"lastname":"Cunningham","firstname":"Johnathon","id":9107187},{"lastname":"Chaney","firstname":"Quentin","id":7630367},{"lastname":"Cervantes","firstname":"Lailah","id":4963591},{"lastname":"Cowan","firstname":"Xiomara","id":8529193},{"lastname":"Chandler","firstname":"Andreas","id":9396189},{"lastname":"Clarke","firstname":"Roger","id":9839807},{"lastname":"Case","firstname":"Ishaan","id":9246398},{"lastname":"Cobb","firstname":"Xiomara","id":2557964},{"lastname":"Clark","firstname":"Lindsey","id":6358724},{"lastname":"Cameron","firstname":"Jocelynn","id":3729037},{"lastname":"Cisneros","firstname":"Dylan","id":7031890},{"lastname":"Conley","firstname":"Jeffrey","id":6094367},{"lastname":"Chen","firstname":"Layton","id":8567125},{"lastname":"Cox","firstname":"Carmelo","id":7879002},{"lastname":"Carroll","firstname":"Frankie","id":2900891},{"lastname":"Cabrera","firstname":"Emmett","id":7451327},{"lastname":"Carpenter","firstname":"Ralph","id":1622846},{"lastname":"Colon","firstname":"Denise","id":7577613},{"lastname":"Chan","firstname":"Lindsey","id":7731718},{"lastname":"Cruz","firstname":"Karley","id":8369011},{"lastname":"Collier","firstname":"Lea","id":5909837},{"lastname":"Collins","firstname":"Dakota","id":4746735},{"lastname":"Casey","firstname":"Zaiden","id":1715558},{"lastname":"Cooper","firstname":"Gunner","id":8133271},{"lastname":"Cantu","firstname":"River","id":3261409},{"lastname":"Carrillo","firstname":"Karlee","id":7989203},{"lastname":"Church","firstname":"Jeffrey","id":9514803},{"lastname":"Christian","firstname":"Nyla","id":5684726},{"lastname":"Crosby","firstname":"Ari","id":4662748},{"lastname":"Chambers","firstname":"Melvin","id":8667388},{"lastname":"Cochran","firstname":"Mariam","id":5478055},{"lastname":"Caldwell","firstname":"Noemi","id":2095436},{"lastname":"Cantrell","firstname":"Leanna","id":5189643},{"lastname":"Cooley","firstname":"Melvin","id":8204292},{"lastname":"Chapman","firstname":"Jamarcus","id":7837935},{"lastname":"Chase","firstname":"Lindsey","id":1441054},{"lastname":"Carrillo","firstname":"Caylee","id":1045034},{"lastname":"Cantu","firstname":"Saul","id":2249062},{"lastname":"Compton","firstname":"Marely","id":4173740},{"lastname":"Chan","firstname":"Parker","id":3748888},{"lastname":"Conway","firstname":"Ryleigh","id":8674728},{"lastname":"Cooley","firstname":"Jesus","id":7100533},{"lastname":"Chang","firstname":"Karla","id":9117033},{"lastname":"Carney","firstname":"Milagros","id":4404773},{"lastname":"Casey","firstname":"Leroy","id":4126226},{"lastname":"Cobb","firstname":"Carmelo","id":3421008},{"lastname":"Carey","firstname":"Greta","id":7502300},{"lastname":"Cooke","firstname":"Alessandra","id":1889475},{"lastname":"Cline","firstname":"Izabella","id":8201947},{"lastname":"Coffey","firstname":"Kash","id":3571867},{"lastname":"Campos","firstname":"Peter","id":7528035},{"lastname":"Chung","firstname":"Beau","id":3831598},{"lastname":"Conner","firstname":"Terrence","id":9710867},{"lastname":"Charles","firstname":"Piper","id":9882885},{"lastname":"Callahan","firstname":"Elaina","id":7006438},{"lastname":"Combs","firstname":"Agustin","id":3856698},{"lastname":"Chapman","firstname":"Jaime","id":2363347},{"lastname":"Cabrera","firstname":"Brittany","id":5689857},{"lastname":"Cunningham","firstname":"Ali","id":1351935},{"lastname":"Chaney","firstname":"Makai","id":2635152},{"lastname":"Choi","firstname":"Gunner","id":8447725},{"lastname":"Cross","firstname":"Hailie","id":3636638},{"lastname":"Conley","firstname":"Ibrahim","id":9579723},{"lastname":"Cole","firstname":"Amare","id":8366076},{"lastname":"Clay","firstname":"Noelle","id":6273539},{"lastname":"Conrad","firstname":"Grace","id":3792904},{"lastname":"Chavez","firstname":"Ahmed","id":2924258},{"lastname":"Cuevas","firstname":"Dominik","id":4296479},{"lastname":"Chandler","firstname":"Harley","id":7278177},{"lastname":"Copeland","firstname":"Jensen","id":6834757},{"lastname":"Case","firstname":"Mercedes","id":9025400},{"lastname":"Contreras","firstname":"Payten","id":2081002},{"lastname":"Clements","firstname":"Kian","id":8923454},{"lastname":"Cox","firstname":"Karli","id":2568649},{"lastname":"Cameron","firstname":"Mia","id":8495214},{"lastname":"Christensen","firstname":"Brendon","id":6189788},{"lastname":"Castillo","firstname":"Josue","id":2016682},{"lastname":"Campbell","firstname":"Deshawn","id":2408567},{"lastname":"Craig","firstname":"Ethan","id":9356284},{"lastname":"Cordova","firstname":"Diamond","id":2541748},{"lastname":"Cisneros","firstname":"Saniya","id":4607073},{"lastname":"Chase","firstname":"Jaydon","id":3313837},{"lastname":"Collins","firstname":"Felix","id":4766586},{"lastname":"Cook","firstname":"Elsie","id":7740888},{"lastname":"Colon","firstname":"Zaria","id":7278603},{"lastname":"Crosby","firstname":"Robert","id":5780362},{"lastname":"Cortez","firstname":"Mira","id":5367178},{"lastname":"Clark","firstname":"Ryder","id":5203207},{"lastname":"Cruz","firstname":"Eileen","id":5591223},{"lastname":"Cochran","firstname":"Trevon","id":5731381},{"lastname":"Calderon","firstname":"Leila","id":5850495},{"lastname":"Carpenter","firstname":"Kael","id":9275002},{"lastname":"Cantrell","firstname":"Douglas","id":6123025},{"lastname":"Cannon","firstname":"London","id":1479397},{"lastname":"Carson","firstname":"Carina","id":9637708},{"lastname":"Caldwell","firstname":"Raven","id":1164764},{"lastname":"Cherry","firstname":"Zoie","id":1250894},{"lastname":"Cervantes","firstname":"Konnor","id":1463041},{"lastname":"Christian","firstname":"Cedric","id":4774109},{"lastname":"Clayton","firstname":"Branden","id":7115219},{"lastname":"Curry","firstname":"Amber","id":3138119},{"lastname":"Carlson","firstname":"Adrien","id":7626413},{"lastname":"Cardenas","firstname":"Daisy","id":6546933},{"lastname":"Carr","firstname":"Esteban","id":6204396},{"lastname":"Cummings","firstname":"Laurel","id":5172085},{"lastname":"Collier","firstname":"Dominique","id":9557620},{"lastname":"Curtis","firstname":"Kaydence","id":8055071},{"lastname":"Carter","firstname":"Zavier","id":9747362},{"lastname":"Cooper","firstname":"Armani","id":2147645},{"lastname":"Cohen","firstname":"Carmelo","id":9611559},{"lastname":"Church","firstname":"Ishaan","id":5845056},{"lastname":"Calhoun","firstname":"Mia","id":3639450},{"lastname":"Castro","firstname":"Ali","id":7274932},{"lastname":"Cowan","firstname":"Mira","id":3904360},{"lastname":"Cain","firstname":"Samuel","id":4046019},{"lastname":"Clarke","firstname":"Nickolas","id":5727119},{"lastname":"Castaneda","firstname":"Juliana","id":1305558},{"lastname":"Crane","firstname":"Abby","id":4826170},{"lastname":"Costa","firstname":"Martin","id":2918430},{"lastname":"Crawford","firstname":"Josue","id":8938599},{"lastname":"Chen","firstname":"Lizbeth","id":2252000},{"lastname":"Coleman","firstname":"Aliza","id":2903105},{"lastname":"Chambers","firstname":"Kellen","id":9078165},{"lastname":"Camacho","firstname":"Yareli","id":5510820},{"lastname":"Carroll","firstname":"Arielle","id":2188657},{"lastname":"Carson","firstname":"Kaydence","id":5184713},{"lastname":"Cunningham","firstname":"Campbell","id":3960757},{"lastname":"Carney","firstname":"Camila","id":4419537},{"lastname":"Camacho","firstname":"Yusuf","id":2133552},{"lastname":"Colon","firstname":"Mikayla","id":8258302},{"lastname":"Crosby","firstname":"Mireya","id":9876433},{"lastname":"Cardenas","firstname":"Pierre","id":6641025},{"lastname":"Craig","firstname":"Vincent","id":6952239},{"lastname":"Coleman","firstname":"Garrett","id":4595148},{"lastname":"Compton","firstname":"Pranav","id":7226815},{"lastname":"Chandler","firstname":"Celeste","id":9686896},{"lastname":"Cross","firstname":"Elias","id":9263260},{"lastname":"Chase","firstname":"Meredith","id":3146498},{"lastname":"Combs","firstname":"Nickolas","id":3369681},{"lastname":"Carrillo","firstname":"Charlie","id":4978902},{"lastname":"Carlson","firstname":"Alexzander","id":5090741},{"lastname":"Cantrell","firstname":"Daniella","id":7130711},{"lastname":"Carey","firstname":"Makena","id":2981884},{"lastname":"Clayton","firstname":"Liam","id":1302522},{"lastname":"Case","firstname":"Milo","id":6982341},{"lastname":"Cortez","firstname":"Jazlene","id":5995094},{"lastname":"Chang","firstname":"Armani","id":3995416},{"lastname":"Charles","firstname":"Journey","id":2144220},{"lastname":"Chavez","firstname":"Triston","id":9591451},{"lastname":"Conrad","firstname":"Ellis","id":5601963},{"lastname":"Costa","firstname":"Dereon","id":3049492},{"lastname":"Contreras","firstname":"Bo","id":6492385},{"lastname":"Crawford","firstname":"Tyrese","id":4653679},{"lastname":"Curtis","firstname":"Giovanny","id":9582685},{"lastname":"Crane","firstname":"Savanna","id":8813531},{"lastname":"Carr","firstname":"Elvis","id":2955339},{"lastname":"Curry","firstname":"Yuliana","id":3996070},{"lastname":"Cameron","firstname":"Yair","id":2938633},{"lastname":"Campos","firstname":"Luke","id":2967014},{"lastname":"Chen","firstname":"Malia","id":8010388},{"lastname":"Choi","firstname":"Duncan","id":9884935},{"lastname":"Callahan","firstname":"Pablo","id":4610689},{"lastname":"Cordova","firstname":"Kelsey","id":9624038},{"lastname":"Copeland","firstname":"Morgan","id":8116860},{"lastname":"Cisneros","firstname":"Taniya","id":6608324},{"lastname":"Carroll","firstname":"Denise","id":6108149},{"lastname":"Cannon","firstname":"Antony","id":3772171},{"lastname":"Coffey","firstname":"Jazmine","id":8465352},{"lastname":"Collins","firstname":"Bryanna","id":3465067},{"lastname":"Cowan","firstname":"Jayvion","id":8848187},{"lastname":"Cummings","firstname":"Alisson","id":9703464},{"lastname":"Clark","firstname":"Keyla","id":4853427},{"lastname":"Chambers","firstname":"Chana","id":4801078},{"lastname":"Castillo","firstname":"Karma","id":9701344},{"lastname":"Cobb","firstname":"Titus","id":9622494},{"lastname":"Conley","firstname":"Jimena","id":9057082},{"lastname":"Calderon","firstname":"Roy","id":1836624},{"lastname":"Cohen","firstname":"Cassius","id":1435879},{"lastname":"Cruz","firstname":"Carlee","id":3853064},{"lastname":"Chung","firstname":"Braylen","id":8410052},{"lastname":"Clay","firstname":"Maeve","id":3709575},{"lastname":"Cooper","firstname":"Brent","id":5962469},{"lastname":"Cooley","firstname":"Maci","id":8988165},{"lastname":"Conner","firstname":"Kolton","id":1893514},{"lastname":"Cain","firstname":"Ezequiel","id":4723678},{"lastname":"Caldwell","firstname":"Genesis","id":5380051},{"lastname":"Cline","firstname":"Diana","id":8360636},{"lastname":"Cochran","firstname":"Cassandra","id":9023487},{"lastname":"Clements","firstname":"Brendon","id":5425992},{"lastname":"Cantu","firstname":"Karter","id":4617236},{"lastname":"Clarke","firstname":"Alice","id":6036045},{"lastname":"Christensen","firstname":"Anahi","id":6469093},{"lastname":"Carter","firstname":"Heather","id":6655788},{"lastname":"Carpenter","firstname":"Michelle","id":3818114},{"lastname":"Cook","firstname":"Kash","id":8252009},{"lastname":"Castro","firstname":"Kasen","id":6172503},{"lastname":"Calhoun","firstname":"Nina","id":7370352},{"lastname":"Cherry","firstname":"Daniel","id":9146990},{"lastname":"Cuevas","firstname":"Cameron","id":3524024},{"lastname":"Cooke","firstname":"Ibrahim","id":6503044},{"lastname":"Chan","firstname":"Lainey","id":4543881},{"lastname":"Cabrera","firstname":"Charlie","id":2650013},{"lastname":"Castaneda","firstname":"Edgar","id":8271424},{"lastname":"Collier","firstname":"Charlize","id":6211542},{"lastname":"Chapman","firstname":"Zackery","id":1280925},{"lastname":"Chaney","firstname":"Shea","id":5032839},{"lastname":"Cervantes","firstname":"Tobias","id":4341689},{"lastname":"Cox","firstname":"Deven","id":8559425},{"lastname":"Campbell","firstname":"Ellen","id":9737038},{"lastname":"Cole","firstname":"Sonny","id":1269822},{"lastname":"Christian","firstname":"Alia","id":2478810},{"lastname":"Church","firstname":"Martin","id":9274971},{"lastname":"Casey","firstname":"Lyric","id":9646504},{"lastname":"Conway","firstname":"Genesis","id":4438936},{"lastname":"Cummings","firstname":"Abigail","id":9038356},{"lastname":"Chavez","firstname":"Ian","id":2924828},{"lastname":"Cardenas","firstname":"Kyle","id":4476901},{"lastname":"Cooke","firstname":"Meredith","id":7499511},{"lastname":"Coleman","firstname":"Dylan","id":7787224},{"lastname":"Chaney","firstname":"Madelynn","id":6648802},{"lastname":"Cantrell","firstname":"Ryleigh","id":6638314},{"lastname":"Cooley","firstname":"Laney","id":9624793},{"lastname":"Cabrera","firstname":"Leanna","id":4714519},{"lastname":"Contreras","firstname":"Keira","id":2564864},{"lastname":"Cooper","firstname":"Coby","id":7773707},{"lastname":"Cline","firstname":"Kolby","id":2004765},{"lastname":"Casey","firstname":"Nylah","id":8695171},{"lastname":"Cruz","firstname":"Ignacio","id":8610677},{"lastname":"Chandler","firstname":"Karsyn","id":6943295},{"lastname":"Curtis","firstname":"Cora","id":5184658},{"lastname":"Coffey","firstname":"Zaria","id":6645000},{"lastname":"Carr","firstname":"Joslyn","id":6839754},{"lastname":"Chapman","firstname":"Chandler","id":9379658},{"lastname":"Clay","firstname":"Jeffery","id":4270348},{"lastname":"Chung","firstname":"Ian","id":5312896},{"lastname":"Carroll","firstname":"Jaxson","id":6893171},{"lastname":"Clements","firstname":"Phoebe","id":9169858},{"lastname":"Conrad","firstname":"Erin","id":2487591},{"lastname":"Cox","firstname":"Meredith","id":6211718},{"lastname":"Cantu","firstname":"Izaiah","id":7599138},{"lastname":"Chan","firstname":"Kaley","id":4287053},{"lastname":"Cross","firstname":"Eve","id":3739220},{"lastname":"Cobb","firstname":"Mireya","id":1758747},{"lastname":"Cohen","firstname":"Makhi","id":6092402},{"lastname":"Camacho","firstname":"Kaylyn","id":2709959},{"lastname":"Crawford","firstname":"Dalton","id":5226802},{"lastname":"Carney","firstname":"Abel","id":7582688},{"lastname":"Copeland","firstname":"Zayden","id":9152049},{"lastname":"Cameron","firstname":"Brian","id":3375746},{"lastname":"Cowan","firstname":"Hillary","id":2818955},{"lastname":"Carlson","firstname":"Lorelei","id":6478763},{"lastname":"Case","firstname":"Selena","id":9599007},{"lastname":"Caldwell","firstname":"Zavier","id":6466055},{"lastname":"Compton","firstname":"Gabriella","id":9157992},{"lastname":"Craig","firstname":"Miranda","id":1189189},{"lastname":"Cunningham","firstname":"Lainey","id":6558988},{"lastname":"Colon","firstname":"Carina","id":2612089},{"lastname":"Cortez","firstname":"Evan","id":4626005},{"lastname":"Callahan","firstname":"Destiny","id":1800100},{"lastname":"Cole","firstname":"Dominic","id":1779109},{"lastname":"Cochran","firstname":"Tyree","id":6853012},{"lastname":"Carpenter","firstname":"Dean","id":7772135},{"lastname":"Chase","firstname":"Kara","id":8993678},{"lastname":"Cherry","firstname":"Kimberly","id":9652718},{"lastname":"Charles","firstname":"Teagan","id":4549502},{"lastname":"Collins","firstname":"Savanna","id":3653433},{"lastname":"Cisneros","firstname":"Angeline","id":8720495},{"lastname":"Curry","firstname":"Steve","id":4140049},{"lastname":"Carson","firstname":"Areli","id":1453104},{"lastname":"Carter","firstname":"Hugh","id":9158829},{"lastname":"Castillo","firstname":"Aaden","id":7164321},{"lastname":"Carey","firstname":"Zara","id":3243707},{"lastname":"Cook","firstname":"Brielle","id":8352451},{"lastname":"Crane","firstname":"Yuliana","id":5799457},{"lastname":"Crosby","firstname":"Claire","id":4792669},{"lastname":"Chang","firstname":"Neveah","id":5278511},{"lastname":"Cain","firstname":"Demarcus","id":2288777},{"lastname":"Choi","firstname":"Mikayla","id":9777879},{"lastname":"Castro","firstname":"Caitlyn","id":9919557},{"lastname":"Cervantes","firstname":"Glenn","id":1423424},{"lastname":"Clarke","firstname":"Darion","id":4468594},{"lastname":"Combs","firstname":"Cael","id":7761226},{"lastname":"Campos","firstname":"Quinton","id":6126911},{"lastname":"Calderon","firstname":"Roman","id":4973980},{"lastname":"Calhoun","firstname":"Paloma","id":7795000},{"lastname":"Clark","firstname":"Rocco","id":5910772},{"lastname":"Campbell","firstname":"Jayvon","id":3802265},{"lastname":"Chen","firstname":"Randy","id":1324644},{"lastname":"Church","firstname":"Hunter","id":7281329},{"lastname":"Castaneda","firstname":"Gideon","id":8830348},{"lastname":"Conner","firstname":"Julianne","id":1411275},{"lastname":"Christensen","firstname":"Mira","id":8455401},{"lastname":"Christian","firstname":"Conor","id":8312747},{"lastname":"Conley","firstname":"Shayla","id":8125358},{"lastname":"Clayton","firstname":"Saniya","id":3074305},{"lastname":"Collier","firstname":"Sincere","id":5777850},{"lastname":"Cannon","firstname":"Mia","id":2880083},{"lastname":"Cordova","firstname":"Michaela","id":6081817},{"lastname":"Cuevas","firstname":"Chad","id":5180297},{"lastname":"Carrillo","firstname":"Anya","id":3490787},{"lastname":"Conway","firstname":"Julio","id":7135386},{"lastname":"Costa","firstname":"Brylee","id":8003810},{"lastname":"Chambers","firstname":"Dexter","id":1034109}]